eje1/eje1.v
module  Conjunto(clk_PC,reset_PC,enable_PC,load_PC,direccion,
  Program_Byte, clk_Fetch,reset_Fetch,enable_Fetch,Instr,Oprnd);

input wire clk_PC,reset_PC,enable_PC,load_PC,clk_Fetch,
reset_Fetch,enable_Fetch;

input wire [11:0] direccion;
output wire [7:0] Program_Byte;
output wire [3:0] Instr,Oprnd;

wire [11:0] PC;



Program_counter P1(clk_PC, reset_PC, enable_PC, load_PC, direccion, PC);
Program_ROM P2(PC,Program_Byte);
Fetch p3(clk_Fetch,reset_Fetch,enable_Fetch, Program_Byte, Instr, Oprnd);

endmodule

////////////////////////////// Program_Counter
module Program_counter(clk, reset, enable, load ,D,Q);

input wire clk, reset, enable, load;
input wire [11:0] D;
output reg [11:0] Q;

always @(posedge clk or posedge reset or posedge load)
   begin
     if (reset) Q <= 0;
     else if (load) Q <= D;
     else if (enable) Q <= Q+1;
     else Q <= Q;
   end
endmodule
/////////////////////////////  Program_memory 64X8
module Program_ROM(direccion,OUT);

input wire [11:0] direccion;
output wire [7:0] OUT;

reg [7:0] memory[0:4095];

initial begin
  $readmemb("memory.list",memory);
end

assign OUT = memory[direccion];

endmodule
////////////////////// Fetch como un flip-flop


module FFD(input wire clk,
           input wire reset,
           input wire enable,
           input wire D,
           output reg Q);

  always @(posedge clk or posedge reset or posedge enable)
    begin
      if (reset) Q <= 1'b0;
      else if (enable) Q <= D;
      else Q <= Q;
    end

endmodule
/// configuración del flip-flop

module flip_flop(clk,reset,enable,D,Q);

input wire clk,reset,enable;
input wire [7:0] D;
output wire [7:0] Q;

FFD F1(clk, reset, enable, D[7], Q[7]);
FFD F2(clk, reset, enable, D[6], Q[6]);
FFD F3(clk, reset, enable, D[5], Q[5]);
FFD F4(clk, reset, enable, D[4], Q[4]);

FFD F5(clk, reset, enable, D[3], Q[3]);
FFD F6(clk, reset, enable, D[2], Q[2]);
FFD F7(clk, reset, enable, D[1], Q[1]);
FFD F8(clk, reset, enable, D[0], Q[0]);
endmodule

/////////////////////////// Fetch

module Fetch(clk,reset,enable,D,comando,fetch);

input wire clk,reset,enable;
input wire [7:0] D;
output wire [3:0] comando, fetch;

FFD F1(clk, reset, enable, D[7], comando[3]);
FFD F2(clk, reset, enable, D[6], comando[2]);
FFD F3(clk, reset, enable, D[5], comando[1]);
FFD F4(clk, reset, enable, D[4], comando[0]);

FFD F5(clk, reset, enable, D[3], fetch[3]);
FFD F6(clk, reset, enable, D[2], fetch[2]);
FFD F7(clk, reset, enable, D[1], fetch[1]);
FFD F8(clk, reset, enable, D[0], fetch[0]);
endmodule

eje1/eje1_tb.v
module Ejercicio_1_tb();

reg clk_PC,reset_PC,enable_PC,load_PC;
reg clk_Fetch,reset_Fetch, enable_Fetch;
reg [11:0] RAM;
wire [7:0] Program_Byte;
wire [3:0] Instr,Oprnd;

//instancia
Conjunto c1(clk_PC,reset_PC,enable_PC,load_PC, RAM,Program_Byte,clk_Fetch,reset_Fetch,enable_Fetch,Instr,Oprnd);




initial begin
   #1 $display(" ");
   $display(" ");
   $display("Implementación de ejercicio 1");
   $display("CP  RP  LP  CF RF EP|     PB     IT   OD");
   $display("____________________|______________________");
   $monitor(" %b    %b  %b   %b   %b %b    %b %b %b | ", clk_PC,reset_PC,load_PC,clk_Fetch,reset_Fetch,enable_PC,Program_Byte,Instr,Oprnd);
   end


    always
    #10 clk_PC = ~clk_PC;
    always
    #10 clk_Fetch = ~clk_Fetch;

initial begin


 RAM = 12'b000000000011;
 clk_PC=0; clk_Fetch=0;

// Valores iniciales
 reset_PC=1; reset_Fetch=1;
 enable_PC=0; enable_Fetch=0; load_PC=0;
///// Comienza programa
//// Contador
#10 reset_PC=0; enable_PC=1;
#10 enable_PC=1; enable_PC=1;
#10 enable_PC=1; enable_PC=1;
#10 enable_PC=1; enable_PC=1;
#10 enable_PC=1; enable_PC=1;
#10 reset_PC=1; reset_PC=0;
#10 load_PC=1; #10 load_PC=0;
#10 enable_PC=1; enable_PC=1;
#10 enable_PC=1; enable_PC=1;
#10 enable_PC=1; enable_PC=1;
#10 enable_PC=1; enable_PC=1;

////
#10 reset_Fetch=0; enable_Fetch=0;
#10 enable_Fetch=1; #10 enable_Fetch=1;
#10 enable_PC=1; #10 enable_PC=1;
#10 enable_PC=1;#10 enable_PC=1;

/////////////////////
#10 reset_PC=1;#10  reset_Fetch=1;


$finish;
end


initial begin
 $dumpfile("Ejercicio_1_tb.vcd");
  $dumpvars(0,Ejercicio_1_tb);
end



endmodule

eje1/Ejercicio_1_tb.vcd
$date
	Sun Nov 08 21:19:13 2020
$end
$version
	Icarus Verilog
$end
$timescale
	1ps
$end
$scope module Ejercicio_1_tb $end
$var wire 8 ! Program_Byte [7:0] $end
$var wire 4 " Oprnd [3:0] $end
$var wire 4 # Instr [3:0] $end
$var reg 12 $ RAM [11:0] $end
$var reg 1 % clk_Fetch $end
$var reg 1 & clk_PC $end
$var reg 1 ' enable_Fetch $end
$var reg 1 ( enable_PC $end
$var reg 1 ) load_PC $end
$var reg 1 * reset_Fetch $end
$var reg 1 + reset_PC $end
$scope module c1 $end
$var wire 1 % clk_Fetch $end
$var wire 1 & clk_PC $end
$var wire 12 , direccion [11:0] $end
$var wire 1 ' enable_Fetch $end
$var wire 1 ( enable_PC $end
$var wire 1 ) load_PC $end
$var wire 1 * reset_Fetch $end
$var wire 1 + reset_PC $end
$var wire 8 - Program_Byte [7:0] $end
$var wire 12 . PC [11:0] $end
$var wire 4 / Oprnd [3:0] $end
$var wire 4 0 Instr [3:0] $end
$scope module P1 $end
$var wire 12 1 D [11:0] $end
$var wire 1 & clk $end
$var wire 1 ( enable $end
$var wire 1 ) load $end
$var wire 1 + reset $end
$var reg 12 2 Q [11:0] $end
$upscope $end
$scope module P2 $end
$var wire 8 3 OUT [7:0] $end
$var wire 12 4 direccion [11:0] $end
$upscope $end
$scope module p3 $end
$var wire 8 5 D [7:0] $end
$var wire 1 % clk $end
$var wire 1 ' enable $end
$var wire 1 * reset $end
$var wire 4 6 fetch [3:0] $end
$var wire 4 7 comando [3:0] $end
$scope module F1 $end
$var wire 1 8 D $end
$var wire 1 % clk $end
$var wire 1 ' enable $end
$var wire 1 * reset $end
$var reg 1 9 Q $end
$upscope $end
$scope module F2 $end
$var wire 1 : D $end
$var wire 1 % clk $end
$var wire 1 ' enable $end
$var wire 1 * reset $end
$var reg 1 ; Q $end
$upscope $end
$scope module F3 $end
$var wire 1 < D $end
$var wire 1 % clk $end
$var wire 1 ' enable $end
$var wire 1 * reset $end
$var reg 1 = Q $end
$upscope $end
$scope module F4 $end
$var wire 1 > D $end
$var wire 1 % clk $end
$var wire 1 ' enable $end
$var wire 1 * reset $end
$var reg 1 ? Q $end
$upscope $end
$scope module F5 $end
$var wire 1 @ D $end
$var wire 1 % clk $end
$var wire 1 ' enable $end
$var wire 1 * reset $end
$var reg 1 A Q $end
$upscope $end
$scope module F6 $end
$var wire 1 B D $end
$var wire 1 % clk $end
$var wire 1 ' enable $end
$var wire 1 * reset $end
$var reg 1 C Q $end
$upscope $end
$scope module F7 $end
$var wire 1 D D $end
$var wire 1 % clk $end
$var wire 1 ' enable $end
$var wire 1 * reset $end
$var reg 1 E Q $end
$upscope $end
$scope module F8 $end
$var wire 1 F D $end
$var wire 1 % clk $end
$var wire 1 ' enable $end
$var wire 1 * reset $end
$var reg 1 G Q $end
$upscope $end
$upscope $end
$upscope $end
$upscope $end
$enddefinitions $end
#0
$dumpvars
0G
xF
0E
xD
0C
xB
0A
x@
0?
x>
0=
x<
0;
x:
09
x8
b0 7
b0 6
bx 5
b0 4
bx 3
b0 2
b11 1
b0 0
b0 /
b0 .
bx -
b11 ,
1+
1*
0)
0(
0'
0&
0%
b11 $
b0 #
b0 "
bx !
$end
#10
b1 .
b1 2
b1 4
1(
0+
1%
1&
#20
0%
0&
#30
b10 .
b10 2
b10 4
1%
1&
#40
0%
0&
#50
b11 .
b11 2
b11 4
1%
1&
#60
b100 .
b100 2
b100 4
0+
0%
0&
#70
b11 .
b11 2
b11 4
1)
1%
1&
#80
0)
0%
0&
#90
b100 .
b100 2
b100 4
1%
1&
#100
0%
0&
#110
b101 .
b101 2
b101 4
1%
1&
#120
0%
0&
#130
b110 .
b110 2
b110 4
0*
1%
1&
#140
x9
x;
x=
bx #
bx 0
bx 7
x?
xA
xC
xE
bx "
bx /
bx 6
xG
1'
0%
0&
#150
b111 .
b111 2
b111 4
1%
1&
#160
0%
0&
#170
b1000 .
b1000 2
b1000 4
1%
1&
#180
0%
0&
#190
b1001 .
b1001 2
b1001 4
1%
1&
#200
b0 .
b0 2
b0 4
1+
0%
0&
#210
09
0;
0=
b0 #
b0 0
b0 7
0?
0A
0C
0E
b0 "
b0 /
b0 6
0G
1*
1%
1&
